gemini3d/__init__.py
gemini3d/archive.py
gemini3d/config.py
gemini3d/coord.py
gemini3d/find.py
gemini3d/hpc.py
gemini3d/job.py
gemini3d/libraries.json
gemini3d/linux_info.py
gemini3d/magcalc.py
gemini3d/magtools.py
gemini3d/model.py
gemini3d/mpi.py
gemini3d/msis.py
gemini3d/namelist.py
gemini3d/plasma.py
gemini3d/read.py
gemini3d/run.py
gemini3d/run_test.py
gemini3d/utils.py
gemini3d/web.py
gemini3d/write.py
gemini3d/wsl.py
gemini3d/compare/__init__.py
gemini3d/compare/__main__.py
gemini3d/compare/efield.py
gemini3d/compare/grid.py
gemini3d/compare/input.py
gemini3d/compare/out.py
gemini3d/compare/plot.py
gemini3d/compare/precip.py
gemini3d/compare/tolerance.json
gemini3d/compare/utils.py
gemini3d/efield/Efield_erf.py
gemini3d/efield/Jcurrent_gaussian.py
gemini3d/efield/__init__.py
gemini3d/grid/__init__.py
gemini3d/grid/cartesian.py
gemini3d/grid/convert.py
gemini3d/grid/gridmodeldata.py
gemini3d/grid/newton_method.py
gemini3d/grid/tilted_dipole.py
gemini3d/grid/uniform.py
gemini3d/hdf5/__init__.py
gemini3d/hdf5/read.py
gemini3d/hdf5/write.py
gemini3d/particles/__init__.py
gemini3d/particles/gaussian2d.py
gemini3d/particles/grid.py
gemini3d/patch/__init__.py
gemini3d/patch/convert.py
gemini3d/patch/plot.py
gemini3d/plot/__init__.py
gemini3d/plot/__main__.py
gemini3d/plot/cartesian.py
gemini3d/plot/constants.py
gemini3d/plot/core.py
gemini3d/plot/curvilinear.py
gemini3d/plot/glow.py
gemini3d/plot/grid.py
gemini3d/plot/input.py
gemini3d/plot/render.py
gemini3d/plot/slices.py
gemini3d/raw/__init__.py
gemini3d/raw/read.py
gemini3d/templates/qsub_template.job
gemini3d/tests/__init__.py
gemini3d/tests/conftest.py
gemini3d/tests/config/__init__.py
gemini3d/tests/config/config_example.nml
gemini3d/tests/config/config_msis2.nml
gemini3d/tests/data/__init__.py
gemini3d/tests/intg/__init__.py
gemini3d/tests/intg/test_dryrun.py
gemini3d/tests/intg/test_grid.py
gemini3d/tests/intg/test_grid_matlab.py
gemini3d/tests/intg/test_model.py
gemini3d/tests/intg/test_msis.py
gemini3d-1.7.0.dist-info/LICENSE.txt
gemini3d-1.7.0.dist-info/METADATA
gemini3d-1.7.0.dist-info/WHEEL
gemini3d-1.7.0.dist-info/top_level.txt
gemini3d-1.7.0.dist-info/RECORD
