Metadata-Version: 2.1
Name: gemini3d
Version: 1.7.0
Summary: 3-D ionospheric model plotting suite
Keywords: mesosphere,stratosphere,thermosphere,ionosphere
Classifier: Development Status :: 5 - Production/Stable
Classifier: Environment :: Console
Classifier: Intended Audience :: Science/Research
Classifier: Operating System :: OS Independent
Classifier: Programming Language :: Python :: 3
Classifier: Topic :: Scientific/Engineering :: Atmospheric Science
Requires-Python: >=3.7
License-File: LICENSE.txt
Requires-Dist: python-dateutil
Requires-Dist: numpy
Requires-Dist: xarray (>=0.16.0)
Requires-Dist: scipy
Requires-Dist: h5py
Requires-Dist: matplotlib (>=3.1)
Provides-Extra: lint
Requires-Dist: flake8 ; extra == 'lint'
Requires-Dist: flake8-bugbear ; extra == 'lint'
Requires-Dist: flake8-builtins ; extra == 'lint'
Requires-Dist: flake8-blind-except ; extra == 'lint'
Requires-Dist: mypy ; extra == 'lint'
Requires-Dist: types-python-dateutil ; extra == 'lint'
Provides-Extra: tests
Requires-Dist: pytest ; extra == 'tests'
